salada/Autoplay.py
salada/EventEmitter.py
salada/Filters.py
salada/Lyrics.py
salada/Node.py
salada/Player.py
salada/PlayerStateManager.py
salada/Queue.py
salada/Rest.py
salada/Salad.py
salada/Track.py
salada/__init__.py
salada/enums.py
salada/exceptions.py
salada/setup.py
salada/voiceclient.py
salada/models/filters.py
salada/models/tracks.py
salada-1.2.7.dist-info/licenses/LICENSE
salada-1.2.7.dist-info/licenses/LICENSE copy
salada-1.2.7.dist-info/METADATA
salada-1.2.7.dist-info/WHEEL
salada-1.2.7.dist-info/top_level.txt
salada-1.2.7.dist-info/RECORD
