Metadata-Version: 2.4
Name: salada
Version: 1.2.7
Summary: A performant lavalink client for python
Home-page: https://github.com/ToddyTheNoobDud/Salad
Author: ToddyTheNoobDud
Project-URL: Homepage, https://github.com/ToddyTheNoobDud/Salad
Project-URL: Repository, https://github.com/ToddyTheNoobDud/Salad.git
Project-URL: Issues, https://github.com/ToddyTheNoobDud/Salad/issues
Requires-Python: >=3.8
License-File: LICENSE
License-File: LICENSE copy
Requires-Dist: aiohttp
Provides-Extra: fast
Requires-Dist: orjson; extra == "fast"
Requires-Dist: msgpack; extra == "fast"
Requires-Dist: aiofiles; extra == "fast"
Provides-Extra: speed
Requires-Dist: ujson; extra == "speed"
Dynamic: home-page
Dynamic: license-file
Dynamic: requires-python
